akde/__init__.py
akde/akde.py
akde-1.0.2.dist-info/LICENSE
akde-1.0.2.dist-info/METADATA
akde-1.0.2.dist-info/WHEEL
akde-1.0.2.dist-info/top_level.txt
akde-1.0.2.dist-info/RECORD
