Metadata-Version: 2.2
Name: akde
Version: 1.0.2
Summary: Multivariate Adaptive Kernel Density Estimation Using Gaussian Mixture Model
Home-page: https://github.com/trungnth/akde
Author: Trung Nguyen
Author-email: trungnth@dnri.vn
Classifier: Programming Language :: Python :: 3
Classifier: License :: OSI Approved :: MIT License
Classifier: Operating System :: OS Independent
Requires-Python: >=3.6
License-File: LICENSE
Requires-Dist: numpy
Requires-Dist: scipy
Dynamic: author
Dynamic: author-email
Dynamic: classifier
Dynamic: description
Dynamic: description-content-type
Dynamic: home-page
Dynamic: requires-dist
Dynamic: requires-python
Dynamic: summary
